Metadata-Version: 2.1
Name: CapsLockMorseCode
Version: 0.1.0
Summary: A silly module to control the keyboard LEDs of the CapsLock, NumLock, and ScrollLock keys to flash Morse Code on Windows, macOS, and Linux.
Home-page: https://github.com/asweigart/capslockmorsecode
Author: Al Sweigart
Author-email: al@inventwithpython.com
License: MIT
Classifier: License :: OSI Approved :: MIT License
Classifier: Programming Language :: Python
Classifier: Programming Language :: Python :: 3
Classifier: Programming Language :: Python :: 3.6
Classifier: Programming Language :: Python :: 3.7
Classifier: Programming Language :: Python :: 3.8
Classifier: Programming Language :: Python :: 3.9
Classifier: Programming Language :: Python :: 3.10
Classifier: Programming Language :: Python :: 3.11
License-File: LICENSE
